<?xml version="1.0"?><prices>  <currency access="aud">    <price access="gold">49.78253453016</price>    <price access="palladium">29.200997695898</price>    <price access="platinum">44.940555070804</price>    <price access="silver">0.66851271578333</price>  </currency>  <currency access="brl">    <price access="gold">118.80311013911</price>    <price access="palladium">69.686474949081</price>    <price access="platinum">107.24800904934</price>    <price access="silver">1.5953665387303</price>  </currency>  <currency access="cad">    <price access="gold">47.429100021466</price>    <price access="palladium">27.820540949081</price>    <price access="platinum">42.816021755221</price>    <price access="silver">0.6369092446127</price>  </currency>  <currency access="chf">    <price access="gold">35.550685901489</price>    <price access="palladium">20.853006117397</price>    <price access="platinum">32.092933247358</price>    <price access="silver">0.47739806348282</price>  </currency>  <currency access="cny">    <price access="gold">239.61949990848</price>    <price access="palladium">140.55388161245</price>    <price access="platinum">216.31348088859</price>    <price access="silver">3.2177687245195</price>  </currency>  <currency access="eur">    <price access="gold">34.043458992096</price>    <price access="palladium">19.968910321075</price>    <price access="platinum">30.732303167651</price>    <price access="silver">0.4571580262085</price>  </currency>  <currency access="gbp">    <price access="gold">24.317537226724</price>    <price access="palladium">14.263965369165</price>    <price access="platinum">21.952349980531</price>    <price access="silver">0.3265519324403</price>  </currency>  <currency access="inr">    <price access="gold">2451.0260714845</price>    <price access="palladium">1437.7011403998</price>    <price access="platinum">2212.6328678343</price>    <price access="silver">32.91399505807</price>  </currency>  <currency access="jpy">    <price access="gold">4738.2796519014</price>    <price access="palladium">2779.3380651174</price>    <price access="platinum">4277.4221852473</price>    <price access="silver">63.628745063482</price>  </currency>  <currency access="mxn">    <price access="gold">592.42013108384</price>    <price access="palladium">347.49654765573</price>    <price access="platinum">534.79980031745</price>    <price access="silver">7.9554083465888</price>  </currency>  <currency access="rub">    <price access="gold">2091.4971675</price>    <price access="palladium">1226.81186375</price>    <price access="platinum">1888.072685</price>    <price access="silver">28.08600375</price>  </currency>  <currency access="usd">    <price access="gold">38.64198</price>    <price access="palladium">22.66627</price>    <price access="platinum">34.88356</price>    <price access="silver">0.51891</price>  </currency>  <currency access="zar">    <price access="gold">469.5579235258</price>    <price access="palladium">275.42912333362</price>    <price access="platinum">423.88749227622</price>    <price access="silver">6.3055335698837</price>  </currency></prices>